omni/__init__.py
omni/address.pyi
omni/base.py
omni/base.pyi
omni/consignment_out.py
omni/consignment_slip.py
omni/contact_information.pyi
omni/contactable.py
omni/contactable.pyi
omni/credit_note.py
omni/currency_value.pyi
omni/customer.py
omni/customer.pyi
omni/document.py
omni/employee.py
omni/employee.pyi
omni/entity.py
omni/errors.py
omni/export.py
omni/identifiable.py
omni/identifiable.pyi
omni/inventory_check.py
omni/inventory_check.pyi
omni/inventory_line.py
omni/invoice.py
omni/media.py
omni/merchandise.py
omni/merchandise.pyi
omni/money_sale_slip.py
omni/named.py
omni/named.pyi
omni/operation.pyi
omni/person.pyi
omni/price.pyi
omni/product.py
omni/receipt.py
omni/return_.py
omni/saft_pt.py
omni/saft_pt.pyi
omni/sale.py
omni/sale.pyi
omni/sale_line.pyi
omni/sale_order.py
omni/sale_snapshot.py
omni/signed_document.py
omni/status.py
omni/stock_adjustment.py
omni/store.py
omni/store.pyi
omni/sub_product.py
omni/supplier.py
omni/system_company.py
omni/task.py
omni/task.pyi
omni/transfer.py
omni/user.py
omni/user.pyi
omni/util.py
omni/value.pyi
omni/web.py
omni/models/__init__.py
omni/models/base.py
omni/models/customer.py
omni/models/entity.py
omni/models/line.py
omni/models/merchandise.py
omni/models/operation.py
omni/models/sale.py
omni_api-0.5.5.dist-info/METADATA
omni_api-0.5.5.dist-info/WHEEL
omni_api-0.5.5.dist-info/top_level.txt
omni_api-0.5.5.dist-info/RECORD
